portfiel/__init__.py
portfiel/main.py
portfiel/mpt.py
portfiel-0.1.4.dist-info/LICENSE.txt
portfiel-0.1.4.dist-info/METADATA
portfiel-0.1.4.dist-info/WHEEL
portfiel-0.1.4.dist-info/top_level.txt
portfiel-0.1.4.dist-info/RECORD
