Metadata-Version: 2.1
Name: portfiel
Version: 0.1.4
Summary: A package for asset allocation
Home-page: https://github.com/Aeroknight786/Efficient-Frontier
Author: Aditya Saha
Author-email: adityaranjha786@gmail.com
Project-URL: Bug Tracker, https://github.com/pypa/sampleproject/issues
Classifier: Programming Language :: Python :: 3
Classifier: License :: OSI Approved :: MIT License
Classifier: Operating System :: OS Independent
Requires-Python: >=3.6
License-File: LICENSE.txt
